datasette_block/__init__.py
datasette_block-0.1.1.dist-info/METADATA
datasette_block-0.1.1.dist-info/WHEEL
datasette_block-0.1.1.dist-info/entry_points.txt
datasette_block-0.1.1.dist-info/top_level.txt
datasette_block-0.1.1.dist-info/RECORD
