Metadata-Version: 2.1
Name: datasette-block
Version: 0.1.1
Summary: Block all access to specific path prefixes
Home-page: https://github.com/simonw/datasette-block
Author: Simon Willison
License: Apache License, Version 2.0
Project-URL: Issues, https://github.com/simonw/datasette-block/issues
Project-URL: CI, https://github.com/simonw/datasette-block/actions
Project-URL: Changelog, https://github.com/simonw/datasette-block/releases
Platform: UNKNOWN
Requires-Python: >=3.6
Requires-Dist: datasette
Provides-Extra: test
Requires-Dist: pytest ; extra == 'test'
Requires-Dist: pytest-asyncio ; extra == 'test'
Requires-Dist: asgi-lifespan ; extra == 'test'
